inject_typed/__init__.py
inject_typed/container.py
inject_typed/test_container.py
inject_typed-0.0.1.dev0.dist-info/LICENSE
inject_typed-0.0.1.dev0.dist-info/METADATA
inject_typed-0.0.1.dev0.dist-info/WHEEL
inject_typed-0.0.1.dev0.dist-info/top_level.txt
inject_typed-0.0.1.dev0.dist-info/RECORD
