Metadata-Version: 2.1
Name: inject-typed
Version: 0.0.1.dev0
Summary: A small example package
Home-page: https://github.com/pbatko/inject-typed
Author: Pawel Batko
Author-email: pawel.batko@gmail.com
License: UNKNOWN
Platform: UNKNOWN
Classifier: Programming Language :: Python :: 3
Classifier: License :: OSI Approved :: Apache Software License
Classifier: Operating System :: OS Independent
Requires-Python: >=3.6
